[{"ar":"بِسْمِ اللَّهِ الرَّحْمَٰنِ الرَّحِيمِ وَالْعَادِيَاتِ ضَبْحًا","id":"Demi kuda perang yang berlari kencang dengan terengah-engah,","tr":"wa<strong>a</strong>l'<u>aa</u>diy<u>aa</u>ti <u>dh</u>ab<u>haa</u><strong>n</strong>","nomor":"1"},{"ar":"فَالْمُورِيَاتِ قَدْحًا","id":"dan kuda yang mencetuskan api dengan pukulan (kuku kakinya),","tr":"fa<strong>a</strong>lmuuriy<u>aa</u>ti qad<u>haa</u><strong>n</strong>","nomor":"2"},{"ar":"فَالْمُغِيرَاتِ صُبْحًا","id":"dan kuda yang menyerang dengan tiba-tiba di waktu pagi,","tr":"fa<strong>a</strong>lmughiir<u>aa</u>ti <u>sh</u>ub<u>haa</u><strong>n</strong>","nomor":"3"},{"ar":"فَأَثَرْنَ بِهِ نَقْعًا","id":"maka ia menerbangkan debu,","tr":"fa-atsarna bihi naq'<u>aa</u><strong>n</strong>","nomor":"4"},{"ar":"فَوَسَطْنَ بِهِ جَمْعًا","id":"dan menyerbu ke tengah-tengah kumpulan musuh,","tr":"fawasa<u>th</u>na bihi jam'<u>aa</u><strong>n</strong>","nomor":"5"},{"ar":"إِنَّ الْإِنْسَانَ لِرَبِّهِ لَكَنُودٌ","id":"sesungguhnya manusia itu sangat ingkar, tidak berterima kasih kepada Tuhannya,","tr":"inna <strong>a</strong>l-ins<u>aa</u>na lirabbihi lakanuud<strong>un</strong>","nomor":"6"},{"ar":"وَإِنَّهُ عَلَىٰ ذَٰلِكَ لَشَهِيدٌ","id":"dan sesungguhnya manusia itu menyaksikan (sendiri) keingkarannya,","tr":"wa-innahu 'al<u>aa</u> <u>dzaa</u>lika lasyahiid<strong>un</strong>","nomor":"7"},{"ar":"وَإِنَّهُ لِحُبِّ الْخَيْرِ لَشَدِيدٌ","id":"dan sesungguhnya dia sangat bakhil karena cintanya kepada harta.","tr":"wa-innahu li<u>h</u>ubbi <strong>a</strong>lkhayri lasyadiid<strong>un</strong>","nomor":"8"},{"ar":"أَفَلَا يَعْلَمُ إِذَا بُعْثِرَ مَا فِي الْقُبُورِ","id":"Maka apakah dia tidak mengetahui apabila dibangkitkan apa yang ada di dalam kubur,","tr":"afal<u>aa</u> ya'lamu i<u>dzaa</u> bu'tsira m<u>aa</u> fii <strong>a</strong>lqubuur<strong>i</strong>","nomor":"9"},{"ar":"وَحُصِّلَ مَا فِي الصُّدُورِ","id":"dan dilahirkan apa yang ada di dalam dada,","tr":"wa<u>h</u>u<u>shsh</u>ila m<u>aa</u> fii <strong>al</strong><u>shsh</u>uduur<strong>i</strong>","nomor":"10"},{"ar":"إِنَّ رَبَّهُمْ بِهِمْ يَوْمَئِذٍ لَخَبِيرٌ","id":"sesungguhnya Tuhan mereka pada hari itu Maha Mengetahui keadaan mereka.","tr":"inna rabbahum bihim yawma-i<u>dz</u>in lakhabiir<strong>un</strong>","nomor":"11"}]